{
	"id": "ed943cea-a9eb-ba26-c407-75348c338076",
	"name": "xy-inc",
	"description": "",
	"order": [
		"80465f52-f200-c4bf-e75a-aa88371bd97a",
		"cd478d94-a169-a4a2-28df-c5e57c2a63b3",
		"cabfb415-259e-131b-216e-da78e769897b",
		"3fcf82c2-8c6d-1ef5-e5eb-2349a7eca64c",
		"229419c6-2d2e-3a35-ae98-1ee9c67b0dd2",
		"50f72235-daf4-5579-a674-e45991a57052",
		"1a48dc31-9521-994d-e27c-cfecd3d921f6",
		"95c829e6-7b2d-0c32-506c-8fbb892d7b65",
		"e1a470dd-697c-c194-7d44-43a9ee973599"
	],
	"folders": [],
	"timestamp": 1478653356272,
	"owner": "666085",
	"public": false,
	"requests": [
		{
			"id": "1a48dc31-9521-994d-e27c-cfecd3d921f6",
			"headers": "Content-Type: application/json\n",
			"url": "localhost:8080/poi",
			"preRequestScript": null,
			"pathVariables": {},
			"method": "POST",
			"data": [],
			"dataMode": "raw",
			"version": 2,
			"tests": null,
			"currentHelper": "normal",
			"helperAttributes": {},
			"time": 1478653672835,
			"name": "save Supermercado",
			"description": "",
			"collectionId": "ed943cea-a9eb-ba26-c407-75348c338076",
			"responses": [],
			"rawModeData": "{\n\t\"name\": \"Supermercado\",\n\t\"x\": \"23\",\n\t\"y\": \"6\"\n}"
		},
		{
			"id": "229419c6-2d2e-3a35-ae98-1ee9c67b0dd2",
			"headers": "Content-Type: application/json\n",
			"url": "localhost:8080/poi",
			"preRequestScript": null,
			"pathVariables": {},
			"method": "POST",
			"data": [],
			"dataMode": "raw",
			"version": 2,
			"tests": null,
			"currentHelper": "normal",
			"helperAttributes": {},
			"time": 1478653622901,
			"name": "save Floricultura",
			"description": "",
			"collectionId": "ed943cea-a9eb-ba26-c407-75348c338076",
			"responses": [],
			"rawModeData": "{\n\t\"name\": \"Floricultura\",\n\t\"x\": \"19\",\n\t\"y\": \"21\"\n}"
		},
		{
			"id": "3fcf82c2-8c6d-1ef5-e5eb-2349a7eca64c",
			"headers": "Content-Type: application/json\n",
			"url": "localhost:8080/poi",
			"preRequestScript": null,
			"pathVariables": {},
			"method": "POST",
			"data": [],
			"dataMode": "raw",
			"version": 2,
			"tests": null,
			"currentHelper": "normal",
			"helperAttributes": {},
			"time": 1478653592934,
			"name": "save Joalheria",
			"description": "",
			"collectionId": "ed943cea-a9eb-ba26-c407-75348c338076",
			"responses": [],
			"rawModeData": "{\n\t\"name\": \"Joalheria\",\n\t\"x\": \"15\",\n\t\"y\": \"12\"\n}"
		},
		{
			"id": "50f72235-daf4-5579-a674-e45991a57052",
			"headers": "Content-Type: application/json\n",
			"url": "localhost:8080/poi",
			"preRequestScript": null,
			"pathVariables": {},
			"method": "POST",
			"data": [],
			"dataMode": "raw",
			"version": 2,
			"tests": null,
			"currentHelper": "normal",
			"helperAttributes": {},
			"time": 1478653645335,
			"name": "save Pub",
			"description": "",
			"collectionId": "ed943cea-a9eb-ba26-c407-75348c338076",
			"responses": [],
			"rawModeData": "{\n\t\"name\": \"Pub\",\n\t\"x\": \"12\",\n\t\"y\": \"8\"\n}"
		},
		{
			"id": "80465f52-f200-c4bf-e75a-aa88371bd97a",
			"headers": "",
			"url": "localhost:8080/poi/findAll",
			"pathVariables": {},
			"preRequestScript": null,
			"method": "GET",
			"collectionId": "ed943cea-a9eb-ba26-c407-75348c338076",
			"data": null,
			"dataMode": "params",
			"name": "findAll",
			"description": "",
			"descriptionFormat": "html",
			"time": 1478653395752,
			"version": 2,
			"responses": [],
			"tests": null,
			"currentHelper": "normal",
			"helperAttributes": {}
		},
		{
			"id": "95c829e6-7b2d-0c32-506c-8fbb892d7b65",
			"headers": "Content-Type: application/json\n",
			"url": "localhost:8080/poi",
			"preRequestScript": null,
			"pathVariables": {},
			"method": "POST",
			"data": [],
			"dataMode": "raw",
			"version": 2,
			"tests": null,
			"currentHelper": "normal",
			"helperAttributes": {},
			"time": 1478653706189,
			"name": "save Churrascaria",
			"description": "",
			"collectionId": "ed943cea-a9eb-ba26-c407-75348c338076",
			"responses": [],
			"rawModeData": "{\n\t\"name\": \"Churrascaria\",\n\t\"x\": \"28\",\n\t\"y\": \"2\"\n}"
		},
		{
			"id": "cabfb415-259e-131b-216e-da78e769897b",
			"headers": "Content-Type: application/json\n",
			"url": "localhost:8080/poi",
			"preRequestScript": null,
			"pathVariables": {},
			"method": "POST",
			"data": [],
			"dataMode": "raw",
			"version": 2,
			"tests": null,
			"currentHelper": "normal",
			"helperAttributes": {},
			"time": 1478653580136,
			"name": "save Posto",
			"description": "",
			"collectionId": "ed943cea-a9eb-ba26-c407-75348c338076",
			"responses": [],
			"rawModeData": "{\n\t\"name\": \"Posto\",\n\t\"x\": \"31\",\n\t\"y\": \"18\"\n}"
		},
		{
			"id": "cd478d94-a169-a4a2-28df-c5e57c2a63b3",
			"headers": "Content-Type: application/json\n",
			"url": "localhost:8080/poi",
			"pathVariables": {},
			"preRequestScript": null,
			"method": "POST",
			"collectionId": "ed943cea-a9eb-ba26-c407-75348c338076",
			"data": [],
			"dataMode": "raw",
			"name": "save Lanchonete",
			"description": "",
			"descriptionFormat": "html",
			"time": 1478653473110,
			"version": 2,
			"responses": [],
			"tests": null,
			"currentHelper": "normal",
			"helperAttributes": {},
			"rawModeData": "{\n\t\"name\": \"Lanchonete\",\n\t\"x\": \"27\",\n\t\"y\": \"12\"\n}"
		},
		{
			"id": "e1a470dd-697c-c194-7d44-43a9ee973599",
			"headers": "",
			"url": "localhost:8080/poi/findPoisNearTo?x=20&y=10&maxDistance=10",
			"pathVariables": {},
			"preRequestScript": null,
			"method": "GET",
			"collectionId": "ed943cea-a9eb-ba26-c407-75348c338076",
			"data": null,
			"dataMode": "params",
			"name": "findPoisNearTo",
			"description": "",
			"descriptionFormat": "html",
			"time": 1478653775080,
			"version": 2,
			"responses": [],
			"tests": null,
			"currentHelper": "normal",
			"helperAttributes": {}
		}
	]
}